formalgeo/__init__.py
formalgeo/core/__init__.py
formalgeo/core/engine.py
formalgeo/data/__init__.py
formalgeo/data/data.py
formalgeo/parse/__init__.py
formalgeo/parse/basic.py
formalgeo/parse/inverse_parse_m2f.py
formalgeo/parse/inverse_parse_s2n.py
formalgeo/parse/parse_cdl.py
formalgeo/parse/parse_pgdl.py
formalgeo/parse/parse_tgdl.py
formalgeo/problem/__init__.py
formalgeo/problem/condition.py
formalgeo/problem/problem.py
formalgeo/solver/__init__.py
formalgeo/solver/backward_search.py
formalgeo/solver/forward_search.py
formalgeo/solver/interactive.py
formalgeo/tools/__init__.py
formalgeo/tools/output.py
formalgeo/tools/utils.py
FormalGeo-0.0.6.dist-info/LICENSE
FormalGeo-0.0.6.dist-info/METADATA
FormalGeo-0.0.6.dist-info/WHEEL
FormalGeo-0.0.6.dist-info/top_level.txt
FormalGeo-0.0.6.dist-info/RECORD
