Metadata-Version: 2.1
Name: FormalGeo
Version: 0.0.6
Summary: Formal representation and solving for Euclidean plane geometry problems.
Author-email: Xiaokai Zhang <xiaokaizhang1999@163.com>
Project-URL: Homepage, https://github.com/FormalGeo/FormalGeo
Project-URL: Bug Tracker, https://github.com/FormalGeo/FormalGeo/issues
Classifier: Programming Language :: Python :: 3
Classifier: License :: OSI Approved :: MIT License
Classifier: Operating System :: OS Independent
Requires-Python: >=3.10
License-File: LICENSE
Requires-Dist: sympy >=1.10
Requires-Dist: func-timeout >=4.3
Requires-Dist: requests >=2.31
Requires-Dist: chardet ==5.2.0
Requires-Dist: tqdm >=4.66.1
Requires-Dist: graphviz >=0.20.1
